trex/__init__.py
trex/trex.py
trex/tests/__init__.py
trex/tests/test_basic_functions.py
tregex-0.0.1.dist-info/LICENSE
tregex-0.0.1.dist-info/METADATA
tregex-0.0.1.dist-info/WHEEL
tregex-0.0.1.dist-info/top_level.txt
tregex-0.0.1.dist-info/RECORD
